MANIFEST.in
setup.cfg
setup.py
glb_slave/__init__.py
glb_slave/__main__.py
glb_slave/command.py
glb_slave/process.py
glb_slave.egg-info/PKG-INFO
glb_slave.egg-info/SOURCES.txt
glb_slave.egg-info/dependency_links.txt
glb_slave.egg-info/entry_points.txt
glb_slave.egg-info/requires.txt
glb_slave.egg-info/top_level.txt
glb_slave/templates/default.jinja2
glb_slave/templates/nginx.conf.jinja2