Metadata-Version: 1.1
Name: glb-slave
Version: 0.0.35
Summary: GLB slave client.
Home-page: https://pypi.python.org/pypi/glb-slave/
Author: Lain
Author-email: softliunaisen@gmail.com
License: UNKNOWN
Platform: UNKNOWN
Classifier: Development Status :: 3 - Alpha
Classifier: License :: OSI Approved :: MIT License
Classifier: Programming Language :: Python :: 2.7
